emotionclassifier/__init__.py
emotionclassifier/classifier.py
emotionclassifier/cli.py
emotionclassifier/fine_tune.py
emotionclassifier/integration.py
emotionclassifier/logger.py
emotionclassifier/model_loader.py
emotionclassifier/preprocess.py
emotionclassifier/suppress_tqdm.py
emotionclassifier/trends.py
emotionclassifier/utils.py
emotionclassifier/visualization.py
emotionclassifier-0.1.4.dist-info/LICENSE
emotionclassifier-0.1.4.dist-info/METADATA
emotionclassifier-0.1.4.dist-info/WHEEL
emotionclassifier-0.1.4.dist-info/RECORD
