Metadata-Version: 2.1
Name: emotionclassifier
Version: 0.1.4
Summary: A flexible emotion classifier with support for multiple models
Home-page: https://github.com/ankit-aglawe/emotionclassifier
License: MIT
Keywords: emotion classification,text emotion classification,emotion prediction python,emotion analysis,NLP,natural language processing,machine learning,deep learning,transformers
Author: Ankit Aglawe
Author-email: aglawe.ankit@gmail.com
Requires-Python: >=3.9,<4.0
Classifier: License :: OSI Approved :: MIT License
Classifier: Programming Language :: Python :: 3
Classifier: Programming Language :: Python :: 3.9
Classifier: Programming Language :: Python :: 3.10
Classifier: Programming Language :: Python :: 3.11
Classifier: Programming Language :: Python :: 3.12
Requires-Dist: click (>=8.1.7,<9.0.0)
Requires-Dist: matplotlib (>=3.9.0,<4.0.0)
Requires-Dist: numpy (>=1.19.2,<2.0.0)
Requires-Dist: pandas (>=2.2.2,<3.0.0)
Requires-Dist: torch (>=2.3.1,<3.0.0)
Requires-Dist: transformers (>=4.42.3,<5.0.0)
Project-URL: Changelog, https://github.com/ankit-aglawe/emotionclassifier/releases
Project-URL: Documentation, https://github.com/ankit-aglawe/emotionclassifier#readme
Project-URL: Repository, https://github.com/ankit-aglawe/emotionclassifier
Project-URL: Source, https://github.com/ankit-aglawe/emotionclassifier
Project-URL: Tracker, https://github.com/ankit-aglawe/emotionclassifier/issues
